square_file_store_helper/__init__.py
square_file_store_helper/main.py
square_file_store_helper/pydantic_models.py
square_file_store_helper-3.1.1.dist-info/WHEEL
square_file_store_helper-3.1.1.dist-info/METADATA
square_file_store_helper-3.1.1.dist-info/RECORD
